square_ragoza/__init__.py
square_ragoza/square_formula.py
square_ragoza-0.10.dist-info/METADATA
square_ragoza-0.10.dist-info/WHEEL
square_ragoza-0.10.dist-info/top_level.txt
square_ragoza-0.10.dist-info/RECORD
