Metadata-Version: 2.1
Name: square-ragoza
Version: 0.10
Summary: Function
Home-page: UNKNOWN
Author: Rauf Gozal
Author-email: <raufgozel@gmail.com>
License: UNKNOWN
Keywords: python,square
Platform: UNKNOWN
Classifier: Development Status :: 1 - Planning
Classifier: Intended Audience :: Developers
Classifier: Programming Language :: Python :: 3
Classifier: Operating System :: Unix
Classifier: Operating System :: MacOS :: MacOS X
Classifier: Operating System :: Microsoft :: Windows
